desearch_py/__init__.py
desearch_py/api.py
desearch_py/openai_utils.py
desearch_py/protocol.py
desearch_py/py.typed
desearch_py-1.0.9.dist-info/METADATA
desearch_py-1.0.9.dist-info/WHEEL
desearch_py-1.0.9.dist-info/top_level.txt
desearch_py-1.0.9.dist-info/RECORD
