Metadata-Version: 2.4
Name: desearch_py
Version: 1.0.9
Summary: A Python SDK for interacting with the Desearch API service.
Author: Desearch
Author-email: 
License: MIT
Classifier: Programming Language :: Python :: 3
Classifier: License :: OSI Approved :: MIT License
Classifier: Operating System :: OS Independent
Requires-Python: >=3.6
Requires-Dist: openai
Requires-Dist: requests
Requires-Dist: typing-extensions
Requires-Dist: pydantic
Dynamic: author
Dynamic: classifier
Dynamic: description
Dynamic: description-content-type
Dynamic: license
Dynamic: requires-dist
Dynamic: requires-python
Dynamic: summary
